vutils/yaml/__init__.py
vutils/yaml/__init__.pyi
vutils/yaml/load.py
vutils/yaml/py.typed
vutils/yaml/utils.py
vutils/yaml/version.py
vutils_yaml-0.1.4.dist-info/LICENSE
vutils_yaml-0.1.4.dist-info/METADATA
vutils_yaml-0.1.4.dist-info/WHEEL
vutils_yaml-0.1.4.dist-info/top_level.txt
vutils_yaml-0.1.4.dist-info/RECORD
