Metadata-Version: 2.1
Name: vutils-yaml
Version: 0.1.4
Summary: Working with YAML format
Home-page: https://github.com/i386x/vutils-yaml
Author: Jiří Kučera
Author-email: sanczes@gmail.com
License: MIT
Project-URL: Bug Reports, https://github.com/i386x/vutils-yaml/issues
Project-URL: Source, https://github.com/i386x/vutils-yaml
Keywords: yaml
Platform: any
Classifier: Development Status :: 1 - Planning
Classifier: Intended Audience :: Developers
Classifier: Intended Audience :: Information Technology
Classifier: Intended Audience :: Science/Research
Classifier: License :: OSI Approved :: MIT License
Classifier: Operating System :: OS Independent
Classifier: Programming Language :: Python
Classifier: Programming Language :: Python :: 3
Classifier: Programming Language :: Python :: 3 :: Only
Classifier: Topic :: Software Development :: Libraries :: Python Modules
Classifier: Topic :: Utilities
Requires-Python: <4,>=3.7
License-File: LICENSE
Requires-Dist: PyYAML
Requires-Dist: vutils-python
Requires-Dist: vutils-validator
Provides-Extra: dev
Requires-Dist: check-manifest ; extra == 'dev'
Provides-Extra: test
Requires-Dist: coverage ; extra == 'test'
